{
  "title": "DIY！簡単棚をDIYで完成！",
  "platform": "YouTube Shorts",
  "resolution": "1080x1920",
  "aspect_ratio": "9:16",
  "duration_sec": 60,
  "target_audience": "20-30代女性、DIYに関心のある層",
  "hook": "賃貸明けでも簡単にできるDIY、棚をDIYで終わらせちゃいましょう！",
  "scenes": [
    {
      "time": "0-5",
      "visual": "棚の完成した様子をアップ。簡単なDIY作業をしながら、木材やネジなどを配置している様子。",
      "narration": "10分で作れる簡単DIY！ 賃貸明けでもすぐに完成する、棚をDIYで終わらせてみましょう！",
      "text_overlay": "DIY, 簡単, 賃貸明け",
      "bgm_cue": "明るく爽やかなBGM（例：ポップ、アップビート）"
    },
    {
      "time": "5-12",
      "visual": "画面に、木材を並べたり、ネジを締めたりする様子を短いカットで映す。動画のテンポを上げる。",
      "narration": "DIYの基礎。木材やネジを組み合わせて、お部屋の雰囲気を変えてみましょう。",
      "text_overlay": "木材, ネジ, DIY, 組み立て",
      "bgm_cue": "少しテンポの良いBGM（例：音楽に合わせて少し速く）"
    },
    {
      "time": "12-20",
      "visual": "成功したDIY作業を、友人や家族に見せて、お礼を伝えている様子（スマホで写真や動画を映す）。",
      "narration": "完成した棚を写真や動画で共有して、感謝の気持ちを伝えてあげましょう！",
      "text_overlay": "写真, 動画, 感謝",
      "bgm_cue": "笑顔や温かいBGM（例：Upliftingな音楽）"
    },
    {
      "time": "20-35",
      "visual": "棚の完成した様子を、様々な場所で使えるように、複数に分けて映す。  「どんな場所にも合うよ！」といったメッセージ。",
      "narration": "この棚は、リビング、ダイニング、キッチンなど、どんな場所にも合うよ！",
      "text_overlay": "様々な場所, 活用",
      "bgm_cue": "明るくポジティブなBGM（例：エネルギッシュな音楽）"
    },
    {
      "time": "35-45",
      "visual": "チャンネル登録と高評価を促す、動画の最後に表示されるアニメやコールバック図。",
      "narration": "高評価とチャンネル登録、お願いします！",
      "text_overlay": "高評価, チャンネル登録",
      "bgm_cue": "静かな音楽（例：穏やかなBGM）"
    }
  ],
  "cta": "高評価＆チャンネル登録はこちら！",
  "hashtags": [
    "#DIY",
    "#DIY簡単",
    "#DIY棚",
    "#DIYアイデア",
    "#賃貸明け",
    "#簡単DIY",
    "#部屋の雰囲気",
    "#暮らし",
    "#部屋の模様替え"
  ]
}